{
    "connnectData": {
        "title": "Connect with us",
        "icons": [
            "/src/images/Facebook.svg",
            "/src/images/Twitter.svg",
            "/src/images/Instagram.svg",
            "/src/images/Youtube.svg"
        ]
    },
    "companyIcons": [
        "/src/images/weather-company.svg",
        "/src/images/The Weather Channel-1.svg",
        "/src/images/Weather Underground.svg"
    ],
    "corporateLinks": [
        "Feedback",
        "Weather API",
        "News Room"
    ],
    "legalLinks": [
        "Terms of Use",
        "Privacy Policy",
        "Accessibility Statement",
        "Data Vendors"
    ],
    "attributionIcons": [
        "/src/images/Georgia.svg",
        "/src/images/essential.svg"
    ],
    "privacyPara": "We recognise our responsibility to use data and technology for good. We may use or share your data with our data vendors. Take control of your data.",
    "privacyLinks": [
        "Data Rights"
    ],
    "copyrightText": "© The Weather Company, LLC 2024"
}